extrator_fbds/__init__.py
extrator_fbds/fbds_async_scraper.py
extrator_fbds/fbds_core.py
extrator_fbds/fbds_ocr.py
extrator_fbds/fbds_retry_failures.py
extrator_fbds/run_fbds_ocr_batch.py
extrator_fbds/run_fbds_ocr_batch_mp.py
extrator_fbds-0.1.2.dist-info/licenses/LICENSE
extrator_fbds-0.1.2.dist-info/METADATA
extrator_fbds-0.1.2.dist-info/WHEEL
extrator_fbds-0.1.2.dist-info/entry_points.txt
extrator_fbds-0.1.2.dist-info/top_level.txt
extrator_fbds-0.1.2.dist-info/RECORD
