Metadata-Version: 2.4
Name: extrator_fbds
Version: 0.1.2
Summary: Async scraper and OCR tools for FBDS (geo.fbds.org.br) geodata
Author: CEPAD-IFSP
License-Expression: MIT
Project-URL: Homepage, https://github.com/CEPAD-IFSP/extrator_fbds
Project-URL: Repository, https://github.com/CEPAD-IFSP/extrator_fbds
Project-URL: Issues, https://github.com/CEPAD-IFSP/extrator_fbds/issues
Keywords: fbds,scraper,ocr,geodata,brasil
Classifier: Development Status :: 4 - Beta
Classifier: Intended Audience :: Science/Research
Classifier: Programming Language :: Python :: 3
Classifier: Programming Language :: Python :: 3.8
Classifier: Programming Language :: Python :: 3.9
Classifier: Programming Language :: Python :: 3.10
Classifier: Programming Language :: Python :: 3.11
Classifier: Programming Language :: Python :: 3.12
Classifier: Topic :: Scientific/Engineering :: GIS
Classifier: Operating System :: OS Independent
Requires-Python: >=3.8
License-File: LICENSE
Requires-Dist: httpx[http2]>=0.24.0
Requires-Dist: h2>=4.1.0
Requires-Dist: beautifulsoup4>=4.11.0
Requires-Dist: pytesseract>=0.3.10
Requires-Dist: Pillow>=9.0.0
Provides-Extra: dev
Requires-Dist: pytest>=7.0.0; extra == "dev"
Requires-Dist: black>=22.0.0; extra == "dev"
Requires-Dist: ruff>=0.0.260; extra == "dev"
Requires-Dist: build>=1.0.0; extra == "dev"
Requires-Dist: twine>=5.0.0; extra == "dev"
Dynamic: license-file
